async_http2-0.1.1.dist-info/METADATA
async_http2-0.1.1.dist-info/WHEEL
async_http2/__init__.py
async_http2/__init__.pyi
async_http2/py.typed
async_http2/async_http2.cpython-39-i386-linux-gnu.so
async_http2-0.1.1.dist-info/RECORD
