Metadata-Version: 2.1
Name: async_http2
Version: 0.1.1
Summary: asyncio-compatible HTTP2 client for Python based on `reqwest` Rust crate and
Keywords: python,http2,asyncio
Author: alekseyl@list.ru
Author-email: alekseyl@list.ru
License: MIT
Project-URL: Source Code, https://github.com/alekseyl1992/async_http2
